{
  "post_id": 1038,
  "slug": "132-where-silence-has-lease-tng-2-02",
  "title": "#132: Where Silence Has Lease (TNG 2.02)",
  "date": "2019-10-29T03:35:51",
  "link": "https://trekamdienstag.de/2019/10/29/132-where-silence-has-lease-tng-2-02/",
  "comment_count": 25,
  "comments": [
    {
      "comment_id": 17570,
      "date": "2024-09-27T20:51:58",
      "author_name": "Benedikt",
      "content": "<p>Humanismus ist bei weitem nicht auf den agnostischen Humanismus beschränkt.<br />\n&#8222;Wissenschaft&#8220; und &#8222;Spiritualität&#8220; werden erst seit dem 19. Jhd. von manchen als Gegensätze gesehen.</p>\n<div class=\"cld-like-dislike-wrap cld-template-2\">\n    <div class=\"cld-like-wrap  cld-common-wrap\">\n    <a href=\"javascript:void(0)\" class=\"cld-like-trigger cld-like-dislike-trigger  \" title=\"Mag ich!\" data-comment-id=\"17570\" data-trigger-type=\"like\" data-restriction=\"cookie\" data-already-liked=\"0\">\n                        <i class=\"fas fa-heart\"></i>\n                </a>\n    <span class=\"cld-like-count-wrap cld-count-wrap\">    </span>\n</div></div>",
      "parent": 0,
      "status": "approved"
    },
    {
      "comment_id": 17568,
      "date": "2024-09-27T19:08:59",
      "author_name": "Benedikt",
      "content": "<p>“You can’t see the Infinite. ’Cos it’s infinite.”<br />\n&#8222;I HAVE.&#8220;<br />\n“All right, what did it look like?”<br />\n&#8222;IT’S BLUE.”</p>\n<div class=\"cld-like-dislike-wrap cld-template-2\">\n    <div class=\"cld-like-wrap  cld-common-wrap\">\n    <a href=\"javascript:void(0)\" class=\"cld-like-trigger cld-like-dislike-trigger  \" title=\"Mag ich!\" data-comment-id=\"17568\" data-trigger-type=\"like\" data-restriction=\"cookie\" data-already-liked=\"0\">\n                        <i class=\"fas fa-heart\"></i>\n                </a>\n    <span class=\"cld-like-count-wrap cld-count-wrap\">    </span>\n</div></div>",
      "parent": 0,
      "status": "approved"
    },
    {
      "comment_id": 17567,
      "date": "2024-09-27T19:04:00",
      "author_name": "Benedikt",
      "content": "<p>Die Menschen haben nie geglaubt, daß die Erde eine Scheibe sei. Man kann es vermuten für eine Zeit am Anfang der frühen Hochkulturen, aber selbst dafür gibt es keine Belege. Seit wir Aussagen über die Form der Erde haben, wird sie immer als Kugel (im Zentrum des Universums) bezeichnet. Einzelne Sonderlinge gab es schon in der Antike, aber auch diese wurden damals schon nicht ernst genommen.<br />\nDie Vorstellung von den dummen Flacherdlern im Mittelalter (und der frühen Neuzeit) geht auf Washington Irving und andere kirchenfeindliche Schriftsteller des 19. Jhd. zurück.</p>\n<div class=\"cld-like-dislike-wrap cld-template-2\">\n    <div class=\"cld-like-wrap  cld-common-wrap\">\n    <a href=\"javascript:void(0)\" class=\"cld-like-trigger cld-like-dislike-trigger  \" title=\"Mag ich!\" data-comment-id=\"17567\" data-trigger-type=\"like\" data-restriction=\"cookie\" data-already-liked=\"0\">\n                        <i class=\"fas fa-heart\"></i>\n                </a>\n    <span class=\"cld-like-count-wrap cld-count-wrap\">1    </span>\n</div></div>",
      "parent": 0,
      "status": "approved"
    },
    {
      "comment_id": 10613,
      "date": "2022-11-01T22:53:41",
      "author_name": "Ohrwell",
      "content": "<p>Seitdem ich mir die Folge nach langer Zeit mal wieder angesehen habe, habe ich darüber nachgedacht, warum man für Nagilum ein solch verzerrtes Äußeres gewählt hat. Ich spekuliere ein wenig: wie würde auf uns ein Beobachter wirken, wenn wir unter einem Mikroskop leben würden? Wir würden sicherlich auch nur etwas 1000fach Vergrößertes erkennen können.</p>\n<div class=\"cld-like-dislike-wrap cld-template-2\">\n    <div class=\"cld-like-wrap  cld-common-wrap\">\n    <a href=\"javascript:void(0)\" class=\"cld-like-trigger cld-like-dislike-trigger  \" title=\"Mag ich!\" data-comment-id=\"10613\" data-trigger-type=\"like\" data-restriction=\"cookie\" data-already-liked=\"0\">\n                        <i class=\"fas fa-heart\"></i>\n                </a>\n    <span class=\"cld-like-count-wrap cld-count-wrap\">    </span>\n</div></div>",
      "parent": 0,
      "status": "approved"
    },
    {
      "comment_id": 6029,
      "date": "2021-07-24T19:06:08",
      "author_name": "Lakonia",
      "content": "<p>Bezüglich Dr. Pulaski denke ich, dass sie ein zwiespältigiges Verhältnis zu Data hat. Sie tut sich schwer mit einem Androiden auf dieser Ebene umgehen zu müssen und fordert ihn (gerade deshalb?) heraus&#8230;. und sich selbst dadurch auch. </p>\n<p>Immerhin nennt sie ihn 2x &#8222;Mr. Data&#8220; und entschuldigt sich direkt für ihre respektlosen Anmerkungen. Sie scheint mir ihrerseits bemüht darum zu sein, in dem Androiden &#8222;jemanden&#8220; zu entdecken, der denselben Respekt verdient wie der Rest der Crew.</p>\n<div class=\"cld-like-dislike-wrap cld-template-2\">\n    <div class=\"cld-like-wrap  cld-common-wrap\">\n    <a href=\"javascript:void(0)\" class=\"cld-like-trigger cld-like-dislike-trigger  \" title=\"Mag ich!\" data-comment-id=\"6029\" data-trigger-type=\"like\" data-restriction=\"cookie\" data-already-liked=\"0\">\n                        <i class=\"fas fa-heart\"></i>\n                </a>\n    <span class=\"cld-like-count-wrap cld-count-wrap\">    </span>\n</div></div>",
      "parent": 0,
      "status": "approved"
    },
    {
      "comment_id": 6000,
      "date": "2021-07-21T17:05:49",
      "author_name": "Mister Incredible",
      "content": "<p>Moin zusammen,</p>\n<p>&#8222;&#8230;.um fremde Galaxien zu erforschen..&#8220; heißt es im deutschen Vorspann. Statt &#8222;civilizations&#8220;&#8230;  ich mag dem ZDF diesen fürchterlichen Lapsus bis heute nicht verzeihen, zumal doch mehr als klar war, dass sich auch TOS nicht von der Milchstraße entfernen kann. Bei Voyager bekommen wir ja dann spätestens den Hinweis, wie lange es bei tausendfacher Lichtgeschindigkeit dauern würde, unsere Galaxie zu durchqueren. Wurde bei Star Trek eigentlich jemals thematisiert, dass man sich vom galaktischen Zentrum tunlichst fern halten sollte?</p>\n<p>Im Vorspann fiel mir &#8222;special appearance&#8220; für Pulaski auch auf, denn wer zur Stammcrew gehört, wird nicht so betitelt. Genugtuend schauen? Oder genuggetan schauend? Offenbar hat man den Sternenhimmel hinter der Observation Lounge aufgepeppt, oder? Das Flirren der Lichter war jedenfalls neu, aber Undank einer fehlenden Atmosphäre im All eher physikalisch falsch&#8230;</p>\n<p>Dieses rehäugige Dingsbums als Antagonisten fand ich eher nervig und kindisch. Da kommt mal in Jahrmillionen eine neue Spezies vorbei, und Mr. Alien fällt außer meucheln nichts ein? Sehr seltsam. Wo Star Trek, um bei astronomischer Korrektheit zu bleiben, einfach noch mal nachlegen sollte, ist der Umstand, dass auf Reisen durch den Raum einfach mal lange Zeit nichts passiert, weil eben auch überall nur nichts ist. Ja, TV-Serien leben davon, dass was passiert, aber dennoch entsteht der Eindruck, es ginge zu wie im Ameisenhaufen. Sicher hat auch Star Trek einen gewissen Anteil daran, dass viele Zeitgenossen der Meinung sind, dass &#8222;sie&#8220; längst schon hier waren und es vor Leben im Universum wimmelt, das auch noch humanoid sein müsste. Allein bei Voyager wird einmal kurz thematisiert, dass es im Prinzip eine große Langeweile bedeutet sich von A nach B zu begeben. Trotz der atmosphärischen Dichte nicht mein Favorit, diese Folge.</p>\n<div class=\"cld-like-dislike-wrap cld-template-2\">\n    <div class=\"cld-like-wrap  cld-common-wrap\">\n    <a href=\"javascript:void(0)\" class=\"cld-like-trigger cld-like-dislike-trigger  \" title=\"Mag ich!\" data-comment-id=\"6000\" data-trigger-type=\"like\" data-restriction=\"cookie\" data-already-liked=\"0\">\n                        <i class=\"fas fa-heart\"></i>\n                </a>\n    <span class=\"cld-like-count-wrap cld-count-wrap\">    </span>\n</div></div>",
      "parent": 0,
      "status": "approved"
    },
    {
      "comment_id": 3958,
      "date": "2020-11-08T20:20:40",
      "author_name": "Michael Kleu",
      "content": "<p>Ich habe Efiie Briest gemocht. Aber ich denke beim Playboy auch nicht als erstes an Peter Maffay und bei &#8222;Sag niemals nie&#8220; kommt mir nicht gleich Klaus Maria Brandauer in den Sinn, sondern Kim Basinger 🙂</p>\n<p>Ich habe die Folge damals gesehen, kann mich aber nicht mehr daran erinnern, wie ich sie da fand. Als ich sie jetzt zur Vorbereitung auf TaD anschaute, war ich nicht so überwältigt. Nachdem ich mir Eure begeisterte Besprechung angehört habe, habe ich die Folge abends um 23 Uhr im Dunkeln noch einmal angesehen, aber die Wirkung, die die Folge auf Euch hatte, blieb bei mir leider aus.</p>\n<div class=\"cld-like-dislike-wrap cld-template-2\">\n    <div class=\"cld-like-wrap  cld-common-wrap\">\n    <a href=\"javascript:void(0)\" class=\"cld-like-trigger cld-like-dislike-trigger  \" title=\"Mag ich!\" data-comment-id=\"3958\" data-trigger-type=\"like\" data-restriction=\"cookie\" data-already-liked=\"0\">\n                        <i class=\"fas fa-heart\"></i>\n                </a>\n    <span class=\"cld-like-count-wrap cld-count-wrap\">    </span>\n</div></div>",
      "parent": 0,
      "status": "approved"
    },
    {
      "comment_id": 3646,
      "date": "2020-09-17T18:18:36",
      "author_name": "Krassling",
      "content": "<p>So können die Meinungen auseinander gehen. Für mich eine sehr denkwürdige Folge. Mein Lieblingsbeispiel für ein Trope welches ich am liebsten gar nicht sehen möchte. X beliebiges absurd übermächtiges &#8222;Ding&#8220;, ja Mr McCoy, will völlig unnötigerweise alle umbringen und die Crew ist völlig machtlos. Diesen Stuss gibt es oft genug und ich kann jedes mal nur innerlich die Augen verdrehen und denken hoffentlich ist es bald vorbei.</p>\n<p>Pulaski war für mich immer irgendwie ein Fremdkörper. Wer so respektlos mit Kollegen umgeht und seine robophobe Ader raushängt passt einfach nicht zu dem Menschenbild, welches Star Trek sonst vermittelt</p>\n<div class=\"cld-like-dislike-wrap cld-template-2\">\n    <div class=\"cld-like-wrap  cld-common-wrap\">\n    <a href=\"javascript:void(0)\" class=\"cld-like-trigger cld-like-dislike-trigger  \" title=\"Mag ich!\" data-comment-id=\"3646\" data-trigger-type=\"like\" data-restriction=\"cookie\" data-already-liked=\"0\">\n                        <i class=\"fas fa-heart\"></i>\n                </a>\n    <span class=\"cld-like-count-wrap cld-count-wrap\">    </span>\n</div></div>",
      "parent": 0,
      "status": "approved"
    },
    {
      "comment_id": 1911,
      "date": "2020-05-14T09:30:55",
      "author_name": "Asterix",
      "content": "<p>P.s. das Video das ich meine kommt nach dem eigentlichen Video</p>\n<div class=\"cld-like-dislike-wrap cld-template-2\">\n    <div class=\"cld-like-wrap  cld-common-wrap\">\n    <a href=\"javascript:void(0)\" class=\"cld-like-trigger cld-like-dislike-trigger  \" title=\"Mag ich!\" data-comment-id=\"1911\" data-trigger-type=\"like\" data-restriction=\"cookie\" data-already-liked=\"0\">\n                        <i class=\"fas fa-heart\"></i>\n                </a>\n    <span class=\"cld-like-count-wrap cld-count-wrap\">    </span>\n</div></div>",
      "parent": 1910,
      "status": "approved"
    },
    {
      "comment_id": 1910,
      "date": "2020-05-14T09:25:58",
      "author_name": "Asterix",
      "content": "<p>Moin Leute,<br />\nin dem Video über per Anhalter durch die Galaxy ist ein entscheidender fehler drinn. Die Mäuse bekommen überhaupt nicht die Antwort auf 42 sondern zu erst muß Aßer Dent in der Zeit zurück auf die Erde der Steinzeit reisen und dort besitzt er nur noch ein Skrappel Spiel und zieht blind die Frage auf die Antwort das ist 6*9 und erst dann ist die Reise per Anhalter durch die Galaxy zu Ende</p>\n<div class=\"cld-like-dislike-wrap cld-template-2\">\n    <div class=\"cld-like-wrap  cld-common-wrap\">\n    <a href=\"javascript:void(0)\" class=\"cld-like-trigger cld-like-dislike-trigger  \" title=\"Mag ich!\" data-comment-id=\"1910\" data-trigger-type=\"like\" data-restriction=\"cookie\" data-already-liked=\"0\">\n                        <i class=\"fas fa-heart\"></i>\n                </a>\n    <span class=\"cld-like-count-wrap cld-count-wrap\">    </span>\n</div></div>",
      "parent": 1904,
      "status": "approved"
    },
    {
      "comment_id": 1909,
      "date": "2019-11-13T13:59:13",
      "author_name": "Sebastian",
      "content": "<p>Vielen Dank für Deinen faszinierenden Kommentar, der gerade intensiv meine Phantasie beflügelt!</p>\n<div class=\"cld-like-dislike-wrap cld-template-2\">\n    <div class=\"cld-like-wrap  cld-common-wrap\">\n    <a href=\"javascript:void(0)\" class=\"cld-like-trigger cld-like-dislike-trigger  \" title=\"Mag ich!\" data-comment-id=\"1909\" data-trigger-type=\"like\" data-restriction=\"cookie\" data-already-liked=\"0\">\n                        <i class=\"fas fa-heart\"></i>\n                </a>\n    <span class=\"cld-like-count-wrap cld-count-wrap\">    </span>\n</div></div>",
      "parent": 1908,
      "status": "approved"
    },
    {
      "comment_id": 1908,
      "date": "2019-11-13T13:55:05",
      "author_name": "JackJean'n'Walker-Buddy-Movie",
      "content": "<p>Danke für die Episode. Ich musste bei eurer Feststellung, dass die ersten Staffeln eigentlich davon handeln, dass das Weltall unbekannt und gefährlich ist, an eure Mutmaßung vor einigen Casts denken, dass vielleicht die Menschheit an so einer Schwelle oder Grenze steht und deswegen sich diese mächtigen, etwas mystischen Völker für sie Interessieren (wie Q, der Reisende und jetzt Nagilum (und ihnen auf ihre komische Art versuchen, weiterzuhelfen)).<br />\nWenn man den Gedanken konsequent weiterdenkt, könnte man zu dem Schluß kommen, dass Kosinski der Auslöser dafür ist, mit seinen (unwissenentlichem, diffusen) Zusammenbringen von Warp, Universum und Gedanken (vgl. auch später &#8222;Das Experiment&#8220;). Dessen Durchbruch in der Forschung ja offenbar mit dem Beginn von TNG zusammenfällt.<br />\nSpätestens nach &#8222;Der Reisende&#8220; müsste es ein Bataillon von Forschern geben, die das Ganze nachzuvollziehen versuchen.<br />\nKosinski wäre damit mindestens in einer Reihe mit Cochrane zu sehen, dessen Forschung und praktische Umsetzung die Vulkanier auf den Plan rief (parallel zu den Wesen nach Kosinski).<br />\nAber hätte man diesen Bogen konsequent weitergeführt, hätten wir heute eine abgeschlosse Erzählung, bei der es um die transzendente Entrückung der Menschheit gegangen wäre. Gut, dass man da ein paar Schritte kleiner weitergemacht hat und uns viele tolle Folgen Star Trek bescheren konnte 🙂 (und nicht wie Babylon 5 nach vier (umso großartigeren) Staffeln alles erzählt hat).<br />\nFreue mich auf die kommenden Episoden.</p>\n<div class=\"cld-like-dislike-wrap cld-template-2\">\n    <div class=\"cld-like-wrap  cld-common-wrap\">\n    <a href=\"javascript:void(0)\" class=\"cld-like-trigger cld-like-dislike-trigger  \" title=\"Mag ich!\" data-comment-id=\"1908\" data-trigger-type=\"like\" data-restriction=\"cookie\" data-already-liked=\"0\">\n                        <i class=\"fas fa-heart\"></i>\n                </a>\n    <span class=\"cld-like-count-wrap cld-count-wrap\">1    </span>\n</div></div>",
      "parent": 0,
      "status": "approved"
    },
    {
      "comment_id": 1907,
      "date": "2019-11-02T21:09:54",
      "author_name": "Volker",
      "content": "<p>Naja, besonders gruselig empfand ich diese Folge eher nicht, wenn man mal davon absieht wie qualvoll es den Crewmen dahin gerafft hat. Das kann schon verstörend auf ein Kind sein. Zumindest einem Kind aus den 80er Jahren. Anders ist es Heute, wo in diversen CSI Serien wirklich jedes Detail gezeigt wird. Deshalb ist mir eine gute Folge &#8222;Columbo&#8220; tausendmal lieber.<br />\nEine wirkliche Grusel Star Trek Folge steht uns allen noch bevor. Es handelt sich um die Folge, in der niemand die REM Schlafphase erreichen kann und wirklich beängstigende Halluzinationen haben wird.<br />\nBis Dienstag 🙂</p>\n<div class=\"cld-like-dislike-wrap cld-template-2\">\n    <div class=\"cld-like-wrap  cld-common-wrap\">\n    <a href=\"javascript:void(0)\" class=\"cld-like-trigger cld-like-dislike-trigger  \" title=\"Mag ich!\" data-comment-id=\"1907\" data-trigger-type=\"like\" data-restriction=\"cookie\" data-already-liked=\"0\">\n                        <i class=\"fas fa-heart\"></i>\n                </a>\n    <span class=\"cld-like-count-wrap cld-count-wrap\">    </span>\n</div></div>",
      "parent": 0,
      "status": "approved"
    },
    {
      "comment_id": 1906,
      "date": "2019-11-01T11:12:02",
      "author_name": "TaoTao",
      "content": "<p>Ich glaube Picard war wirklich bereit das Schiff zu zerstören. Er konnte sicher hoffen, aber in letzter Konsequenz hätte er es glaube durchgezogen.</p>\n<div class=\"cld-like-dislike-wrap cld-template-2\">\n    <div class=\"cld-like-wrap  cld-common-wrap\">\n    <a href=\"javascript:void(0)\" class=\"cld-like-trigger cld-like-dislike-trigger  \" title=\"Mag ich!\" data-comment-id=\"1906\" data-trigger-type=\"like\" data-restriction=\"cookie\" data-already-liked=\"0\">\n                        <i class=\"fas fa-heart\"></i>\n                </a>\n    <span class=\"cld-like-count-wrap cld-count-wrap\">    </span>\n</div></div>",
      "parent": 1902,
      "status": "approved"
    },
    {
      "comment_id": 1905,
      "date": "2019-10-31T23:55:19",
      "author_name": "Bridge 66",
      "content": "<p>Juhuuu! Es hat geklappt!!!</p>\n<p>Kurz vor Mitternacht kommt hier noch ein kleiner Halloween &#8211; Gruß :</p>\n<p><a href=\"https://youtu.be/3fW6xQelhYM\" rel=\"nofollow ugc\">https://youtu.be/3fW6xQelhYM</a></p>\n<div class=\"cld-like-dislike-wrap cld-template-2\">\n    <div class=\"cld-like-wrap  cld-common-wrap\">\n    <a href=\"javascript:void(0)\" class=\"cld-like-trigger cld-like-dislike-trigger  \" title=\"Mag ich!\" data-comment-id=\"1905\" data-trigger-type=\"like\" data-restriction=\"cookie\" data-already-liked=\"0\">\n                        <i class=\"fas fa-heart\"></i>\n                </a>\n    <span class=\"cld-like-count-wrap cld-count-wrap\">    </span>\n</div></div>",
      "parent": 0,
      "status": "approved"
    },
    {
      "comment_id": 1904,
      "date": "2019-10-31T23:50:29",
      "author_name": "Bridge 66",
      "content": "<p>Hallo, Jungs, hallo Simon, alter Leidensgenosse, </p>\n<p>Auch ich musste mich damals im Deutschunterricht mit der armen Effi langweilen. Aber kennst du schon den Youtube-Kanal &#8222;Sommers Weltliteratur to go&#8220;? In einer seiner frühen Folgen hat er das Mädel auch schon verarztet. Ich hoffe, ich habe endlich geschnallt wie das geht mit dem verlinken :</p>\n<p><a href=\"https://youtu.be/O24jFEA8lpc\" rel=\"nofollow ugc\">https://youtu.be/O24jFEA8lpc</a></p>\n<p>Schau mal rein, du schmeißt dich weg. Kleiner Tipp : am Schluss kommt sogar eine kleine Star Trek Connection. </p>\n<p>Die Folge hat mich jetzt nicht umgehauen. Horror ist bekanntlich nicht mein Ding.<br />\nDie Szene zwischen Data und Pulaski fand ich allerdings richtig ärgerlich. Warum war sie überhaupt auf der Brücke? Hat Picard sie gerufen? Wenn ja warum? Und ihr Blick auf Data hat mir eindeutig gezeigt, dass ihr seine Gegenwart unangenehm ist. Sie musste einfach nur ihren Frust an ihm auslassen. Auch die doppelte Entschuldigung kam ihr nicht leicht über die Lippen. &#8222;Okay, ich muß das jetzt zwar sagen, aber ich muß es nicht mögen.&#8220; Es wäre auch ein denkbar schlechter Zeitpunkt gewesen um Data zu einer Reaktion zu provozieren, um ihn zu studieren oder ihm zu helfen sich zu verbessern. </p>\n<p>Längere Szenen ohne Dialoge hat es auch in früheren Serien schon gegeben, aber die waren dann auch mit spannungsgeladener Musik unterlegt. Ich denke dabei vor allem an &#8222;Mission : Impossible&#8220;, wenn das Team irgendwo ein- bzw. ausbrechen musste, oder wenn Barney unter schwierigsten Bedingungen etwas basteln musste. Das fand ich immer faszinierend, wie dieses Team sich ohne Worte verstanden hatte, sobald ein Plan besprochen und in Gang gesetzt wurde.</p>\n<p>Nein, ich denke, diese Folge muss ich nicht noch einmal sehen. Dagegen freue ich mich schon sehr auf die nächste Woche, wenn eine meiner Lieblingsfolgen besprochen wird. Wir sehen uns dann in der Baker Street 221b&#8230;</p>\n<p>LL&amp;P<br />\nEure Bridge</p>\n<div class=\"cld-like-dislike-wrap cld-template-2\">\n    <div class=\"cld-like-wrap  cld-common-wrap\">\n    <a href=\"javascript:void(0)\" class=\"cld-like-trigger cld-like-dislike-trigger  \" title=\"Mag ich!\" data-comment-id=\"1904\" data-trigger-type=\"like\" data-restriction=\"cookie\" data-already-liked=\"0\">\n                        <i class=\"fas fa-heart\"></i>\n                </a>\n    <span class=\"cld-like-count-wrap cld-count-wrap\">    </span>\n</div></div>",
      "parent": 0,
      "status": "approved"
    },
    {
      "comment_id": 1903,
      "date": "2019-10-31T18:37:45",
      "author_name": "Sebastian",
      "content": "<p>Schwierige Frage. Nagilum kann offenkundig Gedanken lesen. Wie wertvoll ist ein Bluff gegen jemanden, wenn man mehr als nur ein Pokerface braucht, besser gesagt sogar ein Pokermind?</p>\n<p>Ob das fiktive Corbomite aber etwas gebracht hätte, bezweifele ich. Als eine MAD-Waffe (mutually assured destruction) ist es nur bei Gegnern wirksam, die tatsächlich zerstört werden können. Doch auch dafür schien mir Nagilum zu machtvoll.</p>\n<div class=\"cld-like-dislike-wrap cld-template-2\">\n    <div class=\"cld-like-wrap  cld-common-wrap\">\n    <a href=\"javascript:void(0)\" class=\"cld-like-trigger cld-like-dislike-trigger  \" title=\"Mag ich!\" data-comment-id=\"1903\" data-trigger-type=\"like\" data-restriction=\"cookie\" data-already-liked=\"0\">\n                        <i class=\"fas fa-heart\"></i>\n                </a>\n    <span class=\"cld-like-count-wrap cld-count-wrap\">    </span>\n</div></div>",
      "parent": 1902,
      "status": "approved"
    },
    {
      "comment_id": 1902,
      "date": "2019-10-31T18:04:35",
      "author_name": "Michael",
      "content": "<p>Natürlich blufft Picard. Der Bluff wäre besser, wenn er mit Korbomit gedroht hätte. Was ja wohl eindeutige Vorlage hier ist.</p>\n<div class=\"cld-like-dislike-wrap cld-template-2\">\n    <div class=\"cld-like-wrap  cld-common-wrap\">\n    <a href=\"javascript:void(0)\" class=\"cld-like-trigger cld-like-dislike-trigger  \" title=\"Mag ich!\" data-comment-id=\"1902\" data-trigger-type=\"like\" data-restriction=\"cookie\" data-already-liked=\"0\">\n                        <i class=\"fas fa-heart\"></i>\n                </a>\n    <span class=\"cld-like-count-wrap cld-count-wrap\">    </span>\n</div></div>",
      "parent": 1901,
      "status": "approved"
    },
    {
      "comment_id": 1901,
      "date": "2019-10-31T08:21:14",
      "author_name": "Kleiner Bruder",
      "content": "<p>Hallo zusammen!<br />\nTja, ohne die von euch geschilderte Atmosphäre klang eure Nacherzählung der Handlung zunächst, als wäre es der größte Stuss seit &#8222;Catspaw&#8220;. Ganz so schlimm ist es vielleicht nicht.<br />\nDer Teaser steht z.B. nicht ganz zusammenhanglos da, weil die Situation -Riker und Worf auf Aussenmission- ja mit der Yamato wieder aufgegriffen wird. Und auch hier ist Worf kurz vorm Durchdrehen und muss sich beruhigen.<br />\nData und Pulaski &#8211; geschenkt. Ich kann dem Pinocchio-Thema sowieso nicht viel abgewinnen. Will Data wirklich Mensch werden? Das erinnert in letzter Konsequenz an Asimovs &#8222;Der 200Jahre Mann&#8220;, in dem ein Roboter am Ende sogar sterblich werden will. Bei Menschen ist es ja eher das Gegenteil, die versuchen alles mögliche, um weiter zu leben.<br />\nPicards Haltung dazu ist, wenn ich es richtig verstanden habe, reiner Agnostizismus (griechisch für Nicht-Wissen). &#8222;Einige sagen so, die anderen sagen so&#8220;. Klar, gerade im amerikanischen TV darf er keine Meinung äußern, um weder die Wissenschaftsgemeinde noch die Evangelikalen zu verprellen. Natürlich gibt es mehr, als wir sehen können, denn &#8222;von Nichts kommt nichts&#8220; und &#8222;von selbst wird nichts besser sondern endet bei Stillstand und Verfall&#8220;. Die Wissenschaft fordert doch geradezu etwas Ewiges. Und der &#8222;Uhrmacher&#8220; lebt natürlich auch nicht in der Uhr, geschweige denn, dass er ein Teil von ihr wäre.<br />\nOb Picard blufft? Ich bin gar nicht so sicher. Lieber ein Ende mit Schrecken, als ein Schrecken ohne Ende. Aber hier fühlte ich mich doch wieder an Kirk erinnert, und zwar positiv. Reden, Verhandeln? Mit welchem Ziel? Dass nur ein Viertel der Besatzung getötet wird? Klang wenig aussichtsreich.<br />\nHat Nagilum die Menschen am Ende wirklich als aggressiv bezeichnet? So nach dem Motto: &#8222;Ich werde mit euch experimentieren, euch töten &#8211; was, ihr wollt nicht? Seid ihr aber aggressiv!&#8220; ? Dann ist das mein Zitat der Woche.</p>\n<div class=\"cld-like-dislike-wrap cld-template-2\">\n    <div class=\"cld-like-wrap  cld-common-wrap\">\n    <a href=\"javascript:void(0)\" class=\"cld-like-trigger cld-like-dislike-trigger  \" title=\"Mag ich!\" data-comment-id=\"1901\" data-trigger-type=\"like\" data-restriction=\"cookie\" data-already-liked=\"0\">\n                        <i class=\"fas fa-heart\"></i>\n                </a>\n    <span class=\"cld-like-count-wrap cld-count-wrap\">    </span>\n</div></div>",
      "parent": 0,
      "status": "approved"
    },
    {
      "comment_id": 1900,
      "date": "2019-10-30T20:08:46",
      "author_name": "tarantinolover69",
      "content": "<p>Ach Sebastian, das war natürlich der T1000 in T2 nicht der T2000. </p>\n<p>😁</p>\n<div class=\"cld-like-dislike-wrap cld-template-2\">\n    <div class=\"cld-like-wrap  cld-common-wrap\">\n    <a href=\"javascript:void(0)\" class=\"cld-like-trigger cld-like-dislike-trigger  \" title=\"Mag ich!\" data-comment-id=\"1900\" data-trigger-type=\"like\" data-restriction=\"cookie\" data-already-liked=\"0\">\n                        <i class=\"fas fa-heart\"></i>\n                </a>\n    <span class=\"cld-like-count-wrap cld-count-wrap\">    </span>\n</div></div>",
      "parent": 0,
      "status": "approved"
    },
    {
      "comment_id": 1899,
      "date": "2019-10-30T19:38:36",
      "author_name": "TaoTao",
      "content": "<p>Heute schneie ich nur mal für einen kurzen Kommentar rein&#8230;<br />\nIch denke mit Data und seinen Gefühlsregungen verhält es sich wie bei den Vulkaniern und ihrer vermeintlichen Emotionslosigkeit. So wie diese mMn Emotionen haben, mit ihnen nur auf eine bestimmte Art umgehen, zeigt Data Emotionen, die er aber nicht empfinden kann. Ich denke diese menschlichen Verhaltensweisen sind ihm einprogrammiert und dienen dem Miteinader, der Kommunikation. Er zuckt mit den Mundwinkeln, schaut kritisch, belustigt oder getroffen etc., aber er fühlt dies nicht. Das widerspricht sich für mich nicht, im Gegenteil, ich finde es sehr logisch, denn es war ja Soongs Ziel einen Androiden zu bauen, der gut mit Menschen kann. Dass dieser davon „auch was hat“, war dann die hohe Kunst&#8230; das kam erst später.</p>\n<p>Herzliche Grüße<br />\nTaoTao 🖖🏻✌🏻👋🏻</p>\n<div class=\"cld-like-dislike-wrap cld-template-2\">\n    <div class=\"cld-like-wrap  cld-common-wrap\">\n    <a href=\"javascript:void(0)\" class=\"cld-like-trigger cld-like-dislike-trigger  \" title=\"Mag ich!\" data-comment-id=\"1899\" data-trigger-type=\"like\" data-restriction=\"cookie\" data-already-liked=\"0\">\n                        <i class=\"fas fa-heart\"></i>\n                </a>\n    <span class=\"cld-like-count-wrap cld-count-wrap\">3    </span>\n</div></div>",
      "parent": 0,
      "status": "approved"
    },
    {
      "comment_id": 1898,
      "date": "2019-10-30T18:26:26",
      "author_name": "Julien",
      "content": "<p>Was den teaser angeht, ich finde nicht, dass es nichts mit der Rest der Episode zu tun hat. Zunächst, ja, es geht darum zu zeigen, was die Crew in ihrer Freizeit macht. Ausserdem spielt es schon auf die Psychologie der Klingonen an, und versucht zu erklären, warum Worf aud der Yamato so handelt. Zum Verhalten der Klingonen passen auch ihre Legenden und Traditionen.</p>\n<p>Nagilum wird durch eine Klingonische Legende eingeführt, die selber durch Worf auf dem Holodeck eingeführt wird.</p>\n<div class=\"cld-like-dislike-wrap cld-template-2\">\n    <div class=\"cld-like-wrap  cld-common-wrap\">\n    <a href=\"javascript:void(0)\" class=\"cld-like-trigger cld-like-dislike-trigger  \" title=\"Mag ich!\" data-comment-id=\"1898\" data-trigger-type=\"like\" data-restriction=\"cookie\" data-already-liked=\"0\">\n                        <i class=\"fas fa-heart\"></i>\n                </a>\n    <span class=\"cld-like-count-wrap cld-count-wrap\">    </span>\n</div></div>",
      "parent": 0,
      "status": "approved"
    },
    {
      "comment_id": 1897,
      "date": "2019-10-29T15:30:54",
      "author_name": "Victor",
      "content": "<p>Tolle Folge!<br />\nNoch ne kleine Bemerkung am Rande: Jonathan Frakes hatte erst jüngst einen Gastauftritt in der (wohlbemerkt deutschen) Netflix &#8211; Serie &#8222;How to Sell Drugs Online (Fast)&#8220; , in der er als Host im X- Factor Studio über die Tücken des Darknets aufklärt.<br />\nIch dachte erst ich traue meinen Augen nicht 😀<br />\nFalls ihr es sehen wollt, er ist in Episode 2 etwa ab Minute 16 😉<br />\nHabt noch ne schöne Woche und bis nächsten Dienstag!</p>\n<div class=\"cld-like-dislike-wrap cld-template-2\">\n    <div class=\"cld-like-wrap  cld-common-wrap\">\n    <a href=\"javascript:void(0)\" class=\"cld-like-trigger cld-like-dislike-trigger  \" title=\"Mag ich!\" data-comment-id=\"1897\" data-trigger-type=\"like\" data-restriction=\"cookie\" data-already-liked=\"0\">\n                        <i class=\"fas fa-heart\"></i>\n                </a>\n    <span class=\"cld-like-count-wrap cld-count-wrap\">    </span>\n</div></div>",
      "parent": 1895,
      "status": "approved"
    },
    {
      "comment_id": 1896,
      "date": "2019-10-29T15:27:33",
      "author_name": "Michael from Outer Space",
      "content": "<p>Hallo Leute!</p>\n<p>Weil Simon und Sebastian Armus erwähnten, möchte ich auf den Namen des Produzenten hinweisen: Burton Armus. Laut Memory Alpha inspirierte sein Nachname die Autoren zur Benennung des gleichnamigen Wesens. Vielleicht wurde das auch schon im Podcast zur Armus-Folge erklärt. In der 4. Voyager-Staffel gibt es die Episode &#8222;Scientific Method / Verwerfliche Experimente&#8220;, in der die Crewmen von Aliens als Laborratten missbraucht werden. Ein Redshirt stirbt, wodurch Janeway ausrastet und den Fremden droht. Vielleicht muss das Sternenflottenpersonal einen Vertrag unterschreiben, in dem das als Berufsrisiko eingestuft wird. Die Hinterbliebenen bekommen darum auch nur das Standard-Beleidsschreiben zugeschickt. Seufz!</p>\n<p>Die angesprochene Atmospähre, die einen packt und in seinen Bann zieht, habe ich auch in Ansätzen wahrgenommen. Für mich hat es aber nicht ganz funktioniert, das kann am Vorspann liegen, den ich etwas merkwürding finde. Warum machen sich alle Sorgen um Worf und Riker? Ich hatte es so verstanden, dass hier eine falsche Fährte gelegt werden sollte, damit die Zuschauer wirklich glauben, die beiden würden auf einem Planeten eine gefährliche Mission durchführen. Worfs Stachel-Handschuh erinnerte mich an eine ähnliche Waffe, die in der 1. Staffel von Tasha verwendet wurde. Den Vorspann hatte ich vergessen, aber richtig gefährlich kam mir die Simulation nicht vor.</p>\n<p>Nagilum empfand ich beim ersten Anschauen vor vielen Jahren als sehr gruselig, der Effekt mit dem verzerrten Gesicht klappt auch heute noch gut. Merkwürdig finde aber seine Aussage, er wolle ein Drittel bis die Hälfte der Besatzung töten, um alle Arten des Todes zu erforschen. Wie soll das denn bitte ablaufen? Menschen können auf diverse Arten sterben, z.B. durch Krankheiten, Verletzungen, Altersschwäche, Komplikationen während der Geburt, Herzinfarkt, Hirnschlag, Vergiftung, Strahlung, Verdursten, Verhungern, Ersticken etc. Wie möchte Nagilum alle diese Tode künstlich herbeiführen? Außerdem gibt es ja auch außerirdische Besatzungsmitglieder, die eventuell aus unserer Sicht &#8222;exotische&#8220; Todesarten haben. Ich weiß nicht, wie viele verschiedene tödliche Erreger es auf der Erde gibt, aber Nagilum kann die Leute an Bord nicht mit hunderten verschiedener Krankheiten infizieren, zumal er wahrscheinlich auch gar nicht genug über die Menschen und die anderen Spezies auf dem Schiff weiß. Es sei denn, er ist ein omnipotentes, omnipräsentes Wesen wie Q, das schließe ich aber einfach mal aus.</p>\n<p>OK, lassen wir das beiseite. Nagilum möchte also wissen, wie Menschen dem Tod begegnen. Wie begegnen sie denn dem Tod? Indem sie klassische Musik hören und philosophische Gespräche führen? Als die falsche Troi Picards Quartier betritt, sieht man auf dem Korridor kurz jemanden vorbeilaufen, der angesichts des bevorstehenden Untergangs erstaunlich gelassen wirkt. SO würde ich mit dieser Situation nicht umgehen! Picard spricht danach kurz mit Data und schon ist das Problem gelöst, weil Nagilum alles erfahren hat, was er wissen wollte. Captain, es kann manchmal so einfach sein! Falls diese Auseinandersetzung mit dem Tod den Kern der Episode bilden soll, haben sie es ziemlich vermasselt. Dieses Ende finde ich sehr unbefriedigend. Es ist eine typische, aus dem Hut gezauberte Lösung eines Konfliktes.</p>\n<p>Für mich ist &#8222;Where Silence Has Lease&#8220; keine schlechte, aber auch keine gute Folge. Es gibt bessere Episoden mit dichter Atmosphäre, bei denen ich die unlogische Story gerne etwas großzügiger bewerte. Daumen quer.</p>\n<p>MfG</p>\n<p>Michael from Outer Space</p>\n<div class=\"cld-like-dislike-wrap cld-template-2\">\n    <div class=\"cld-like-wrap  cld-common-wrap\">\n    <a href=\"javascript:void(0)\" class=\"cld-like-trigger cld-like-dislike-trigger  \" title=\"Mag ich!\" data-comment-id=\"1896\" data-trigger-type=\"like\" data-restriction=\"cookie\" data-already-liked=\"0\">\n                        <i class=\"fas fa-heart\"></i>\n                </a>\n    <span class=\"cld-like-count-wrap cld-count-wrap\">    </span>\n</div></div>",
      "parent": 0,
      "status": "approved"
    },
    {
      "comment_id": 1895,
      "date": "2019-10-29T15:15:05",
      "author_name": "Don",
      "content": "<p><i>Ach, Simon, lass &#8230; das ist ein zu weites Feld!</i></p>\n<p>SIGOR klang aber eher ein bisschen wie Marcel Reich-Ranicki.</p>\n<p>Mein Radiosender hier in der Gegend spielt im Oktober immer diesen Jingle:<br />\n&#8222;Mein Bär, der hat acht Ecken, es ist ein &#8211; OktoBÄR!&#8220; ^^</p>\n<p>Aber gerade im Deutschunterricht habe ich gemerkt, wie wichtig ein guter Lehrer sein kann. Ich habe dieses Fach jahrelang gehasst. Und plötzlich in der Kursphase, hatten wir einen Lehrer, der sein Fach und die Literatur so sehr geliebt hat, dass er es schaffte, uns alle mitzureißen. Und plötzlich bekam ich da dann auch gute Noten. Also eine Win-Win-Situation, es machte auf einmal Spaß und es zahlte sich sogar aus!</p>\n<p>Also ich wäre durchaus dankbar, wenn man mich darauf hinweist, wenn ich Mundgeruch habe. Ich weiß aber ja aus eigener Erfahrung, wie gehemmt man sein kann, sowas offen auszusprechen.</p>\n<p>Ich hoffe nur, die Blagen kommen jetzt am Donnerstag nicht mit dem Spruch:<br />\n&#8222;Süßes, sonst gibt&#8217;s Mundgeruch!&#8220;</p>\n<p>Schön finde ich auch:<br />\n<a href=\"https://www.youtube.com/watch?v=9S1EzkRpelY\" rel=\"nofollow ugc\">https://www.youtube.com/watch?v=9S1EzkRpelY</a></p>\n<p>Die Star-Trek-Tafelrunde hat z.Zt. eine Artikel-Reihe zu laufen, in der sie sich mit Deutschen in Star Trek befasst, auch Winrich Kolbe kam darin schon vor.</p>\n<p>Im Prinzip gebe ich ja Sebastian recht, Pulaski ist fasziniert von Data und sie mag ihn eigentlich auch sehr, denke ich. Aber hier geht es mir wie Simon, Pulaskis Frage, ob Data weiß, was er da tut und ihn gleichzeitig auch noch als &#8222;Es&#8220; bezeichnet, finde ich unmöglich. Und eigentlich auch ziemlich dämlich!</p>\n<p>Mut zur Stille &#8211; Where Silence Has Lease.<br />\nDiese wortlosen Szenen werden ja auch immer durch so schöne Kleinigkeiten verdeutlicht, z.B. wenn Riker sich mit den Fingern ans Bein tippt.<br />\nÜberhaupt kann man gerade an Riker sehen, wie er im Laufe der Folge immer ungehaltener wird.</p>\n<p>Wie ich ja schon letztens andeutete, finde ich diese Lösung, Geordi irgendwann zur Brücke kommen zu lassen und die Maschinenraum-Kontrolle auf eine der Konsolen zu transferieren, ziemlich bescheuert.<br />\nAber vielleicht hat ja der Agent von LeVar Burton das mit den Produzenten so ausgehandelt, damit Geordi auf diese Weise mehr Screentime erhält?<br />\nZum Glück ist man in späteren Staffeln von diesem Quatsch wieder abgekommen!</p>\n<p>1,4 Parsecs, wieviel Kellicams sind das?</p>\n<p>Fort Boyard 😀<br />\n&#8222;Schlüssel geht an Meer.&#8220;</p>\n<p>In &#8222;Contagion&#8220; hat die Yamato ja dann auch eine ganz andere Signatur.</p>\n<p>Jetzt hätte schon ein zweites Mal in dieser Folge der Worf beinah den Riker getötet. Das ist doch immerhin eine nette Analogie zur Teaser-Szene.<br />\nAuch später nochmal, wo es darum geht, dass Worf sich wieder beruhigen soll.</p>\n<p><i>🎵 Ein Will Riker. Es gibt nur ein&#8216; Will Riker! 🎶</i></p>\n<p>Das ist ja das Fiese am Redshirt-Dasein: Wesley ist schuld, dass sie in diesem Loch überhaupt gefangen sind und Haskell muss es dann ausbaden.</p>\n<p>Gerechte Strafe hin oder her, wenn Picard jetzt den Befehl zum Rausfliegen gegeben hätte, dann hätte Haskell (vielleicht) überlebt. Womöglich ahnte er, dass ihm als Redshirt nur wenige Überlebenschancen bleiben. ^^</p>\n<p>Ja stimmt, Simon, nachdem Riker ihn so anfährt, lächelt Picard wirklich so leicht. Und ich habe nie so recht erfassen können, ob er da nun amüsiert, irritiert, peinlich berührt oder was auch immer ist.</p>\n<p>Diese ganzen Labortest-Situationen haben mich an diese Fairness-Studie mit Kappuzineräffchen erinnert:<br />\n<a href=\"https://www.youtube.com/watch?v=meiU6TxysCg\" rel=\"nofollow ugc\">https://www.youtube.com/watch?v=meiU6TxysCg</a></p>\n<p>Nagilum sagt ja, dass er diese Erscheinung gewählt hat, damit sie ihnen vertraut vorkommt und ihre Erwartungshaltung erfüllt. Ein bisschen wie bei Balok.</p>\n<p>Dieses Sterben von Haskell fand ich auch sehr heftig. Wie der sich die Hände an die Wangen hält und am Ende dann mit gebrochenen Augen und so zusammengekauert liegen bleibt &#8211; alter Schwede!</p>\n<p>Pulaskis Einwand, dass die Selbstzerstörung ja wie das Töten eines Patienten wäre, um ihn von der Krankheit zu heilen, ist ja durchaus berechtigt.</p>\n<p>Och, ich weiß nicht. Gymnopedies find ich eigentlich eine gute Wahl für die letzten Minuten, hat doch was von zur Ruhe kommen.<br />\nErik Satie ist ja oft als Fahrstuhlmusik verpönt, aber ich höre ihn gern. Neben den Gymnopedies mag ich z.B. auch die Gnossiennes sehr.<br />\nUnd Captain Picard hat mal ausnahmsweise nicht was Britisches konsumiert, Henry Purcell, Edward Elgar oder gar die Beatles (&#8222;Help! I need somebody.&#8220;). Nein, der Mann aus La Barre darf endlich mal auch was Französisches genießen!</p>\n<p>Fürs Deaktivieren der Selbstzerstörungs-Sequenz wird der Finger-Scan von Picard und Riker dann interessanterweise nicht mehr benötigt.</p>\n<p>Auch von mir gibt es den Daumen rauf. Ich mag die Folge einfach!</p>\n<div class=\"cld-like-dislike-wrap cld-template-2\">\n    <div class=\"cld-like-wrap  cld-common-wrap\">\n    <a href=\"javascript:void(0)\" class=\"cld-like-trigger cld-like-dislike-trigger  \" title=\"Mag ich!\" data-comment-id=\"1895\" data-trigger-type=\"like\" data-restriction=\"cookie\" data-already-liked=\"0\">\n                        <i class=\"fas fa-heart\"></i>\n                </a>\n    <span class=\"cld-like-count-wrap cld-count-wrap\">    </span>\n</div></div>",
      "parent": 0,
      "status": "approved"
    }
  ]
}